AUTHORS.rst
CONTRIBUTING.rst
HISTORY.rst
MANIFEST.in
README.rst
setup.cfg
setup.py
docs/Makefile
docs/authors.rst
docs/conf.py
docs/contributing.rst
docs/history.rst
docs/index.rst
docs/installation.rst
docs/make.bat
docs/readme.rst
docs/usage.rst
tests/__init__.py
tests/test_zhanutils.py
zhanutils/__init__.py
zhanutils/messenger.py
zhanutils/utils.py
zhanutils.egg-info/PKG-INFO
zhanutils.egg-info/SOURCES.txt
zhanutils.egg-info/dependency_links.txt
zhanutils.egg-info/not-zip-safe
zhanutils.egg-info/top_level.txt